s1flood/__init__.py
s1flood/__version__.py
s1flood/mapFloods.py
s1flood/zscore.py
s1flood-0.0.3.dist-info/LICENSE
s1flood-0.0.3.dist-info/METADATA
s1flood-0.0.3.dist-info/WHEEL
s1flood-0.0.3.dist-info/top_level.txt
s1flood-0.0.3.dist-info/RECORD
