Metadata-Version: 2.1
Name: s1flood
Version: 0.0.3
Summary: UNKNOWN
Home-page: https://github.com/bendv/s1flood
Author: Ben DeVries
Author-email: bdv@uoguelph.ca
License: MIT
Platform: UNKNOWN
Requires-Dist: earthengine-api
Requires-Dist: httplib2shim
